ovos_PHAL_plugin_configuration_provider/__init__.py
ovos_PHAL_plugin_configuration_provider/descriptions.json
ovos_PHAL_plugin_configuration_provider/version.py
ovos_PHAL_plugin_configuration_provider-1.0.0.dist-info/LICENSE
ovos_PHAL_plugin_configuration_provider-1.0.0.dist-info/METADATA
ovos_PHAL_plugin_configuration_provider-1.0.0.dist-info/WHEEL
ovos_PHAL_plugin_configuration_provider-1.0.0.dist-info/entry_points.txt
ovos_PHAL_plugin_configuration_provider-1.0.0.dist-info/top_level.txt
ovos_PHAL_plugin_configuration_provider-1.0.0.dist-info/zip-safe
ovos_PHAL_plugin_configuration_provider-1.0.0.dist-info/RECORD
