Metadata-Version: 2.1
Name: ovos-PHAL-plugin-configuration-provider
Version: 1.0.0
Summary: Configuration provider plugin for OpenVoiceOS hardware abstraction layer
Home-page: https://github.com/OpenVoiceOS/ovos-PHAL-plugin-configuration-provider
Author: AIIX
Author-email: aix.m@outlook.com
License: Apache-2.0
Platform: UNKNOWN
Classifier: Development Status :: 3 - Alpha
Classifier: Intended Audience :: Developers
Classifier: Topic :: Utilities
Classifier: License :: OSI Approved :: Apache Software License
Classifier: Programming Language :: Python :: 3.5
Classifier: Programming Language :: Python :: 3.6
Classifier: Programming Language :: Python :: 3.7
Classifier: Programming Language :: Python :: 3.8
Classifier: Programming Language :: Python :: 3.9
Classifier: Programming Language :: Python :: 3.10
Requires-Dist: ovos-plugin-manager (>=0.0.1)
Requires-Dist: ovos-utils
Requires-Dist: mycroft-messagebus-client
Requires-Dist: ovos-config
